bel_repository/__init__.py
bel_repository/__main__.py
bel_repository/cli.py
bel_repository/constants.py
bel_repository/metadata.py
bel_repository/repository.py
bel_repository/utils.py
bel_repository/version.py
bel_repository-0.1.2.dist-info/LICENSE
bel_repository-0.1.2.dist-info/METADATA
bel_repository-0.1.2.dist-info/WHEEL
bel_repository-0.1.2.dist-info/entry_points.txt
bel_repository-0.1.2.dist-info/top_level.txt
bel_repository-0.1.2.dist-info/RECORD
