Metadata-Version: 2.1
Name: bel-repository
Version: 0.1.2
Summary: A utility for loading data from repositories of BEL documents.
Home-page: https://github.com/pybel/bel-repository
Author: Charles Tapley Hoyt
Author-email: cthoyt@gmail.com
Maintainer: Charles Tapley Hoyt
Maintainer-email: cthoyt@gmail.com
License: MIT
Download-URL: https://github.com/pybel/bel-repository/releases
Project-URL: Bug Tracker, https://github.com/pybel/bel-repository/issues
Project-URL: Source Code, https://github.com/pybel/bel-repository
Keywords: Biological Expression Language,BEL,Domain Specific Language,DSL,Systems Biology,Networks Biology
Platform: UNKNOWN
Classifier: Development Status :: 4 - Beta
Classifier: Environment :: Console
Classifier: Intended Audience :: Developers
Classifier: Intended Audience :: Science/Research
Classifier: License :: OSI Approved :: MIT License
Classifier: Operating System :: OS Independent
Classifier: Programming Language :: Python
Classifier: Programming Language :: Python :: 3.8
Classifier: Programming Language :: Python :: 3.7
Classifier: Programming Language :: Python :: 3.6
Classifier: Programming Language :: Python :: 3 :: Only
Classifier: Topic :: Scientific/Engineering :: Bio-Informatics
Classifier: Topic :: Scientific/Engineering :: Chemistry
Requires-Python: >=3.6
Requires-Dist: pybel (<0.15.0,>=0.14.8)
Requires-Dist: tqdm
Requires-Dist: pandas
Requires-Dist: click
Requires-Dist: dataclasses ; python_version < "3.7"
